{
  "kind": "collectionType",
  "collectionName": "services",
  "info": {
    "name": "service",
    "description": ""
  },
  "options": {
    "increments": true,
    "timestamps": true,
    "draftAndPublish": true
  },
  "pluginOptions": {},
  "attributes": {
    "title": {
      "type": "string",
      "required": true,
      "unique": true
    },
    "metaTitle": {
      "type": "string",
      "required": false,
      "unique": false
    },
    "metaDesc": {
      "type": "string"
    },
    "metaKeyword": {
      "type": "string"
    },
    "category": {
      "model": "category"
    },
    "content": {
      "type": "richtext",
      "required": true
    },
    "banner": {
      "collection": "file",
      "via": "related",
      "allowedTypes": [
        "images"
      ],
      "plugin": "upload",
      "required": true,
      "pluginOptions": {}
    },
    "icon": {
      "model": "file",
      "via": "related",
      "allowedTypes": [
        "images"
      ],
      "plugin": "upload",
      "required": true,
      "pluginOptions": {}
    },
    "slug": {
      "type": "uid",
      "targetField": "title",
      "required": true
    }
  }
}
